fargate_scraper.py
fargate_scraper-0.0.2.dist-info/DESCRIPTION.rst
fargate_scraper-0.0.2.dist-info/METADATA
fargate_scraper-0.0.2.dist-info/RECORD
fargate_scraper-0.0.2.dist-info/WHEEL
fargate_scraper-0.0.2.dist-info/entry_points.txt
fargate_scraper-0.0.2.dist-info/metadata.json
fargate_scraper-0.0.2.dist-info/top_level.txt
