Metadata-Version: 2.0
Name: fargate-scraper
Version: 0.0.2
Summary: A CLI utility for scraping metrics endpoints from AWS Fargate.
Home-page: UNKNOWN
License: UNKNOWN
Platform: UNKNOWN
Requires-Python: >=3.5
Requires-Dist: boto3
